{
  "/alive": {
    "function": "alive",
    "definition": "Check bot"
  },
  "/time": {
    "function": "time",
    "definition": "Check bot time"
  },
  "/feed": {
    "function": "baby_feed",
    "definition": "Add Feeding Information"
  },
  "/diaper": {
    "function": "baby_diaper",
    "definition": "Add Diaper Information"
  },
  "/feed_history": {
    "function": "baby_feed_history",
    "definition": "Graph it"
  },
  "/diaper_history": {
    "function": "baby_diaper_history",
    "definition": "Graph it"
  },
  "/feed_trend_date": {
    "function": "baby_feed_trend_date",
    "definition": "See the feeding trend by date"
  },
  "/diaper_trend_date": {
    "function": "baby_diaper_trend_date",
    "definition": "See the diaper trend by date"
  },
  ,
  "/feed_trend_source": {
    "function": "baby_feed_trend_cat",
    "definition": "See the feeding trend"
  },
  "/diaper_trend_excrement": {
    "function": "baby_diaper_trend_cat",
    "definition": "See the diaper trend"
  }
}